{
  "version": "7",
  "dialect": "postgresql",
  "entries": [
    {
      "idx": 0,
      "version": "7",
      "when": 1762864033494,
      "tag": "0000_dear_la_nuit",
      "breakpoints": true
    },
    {
      "idx": 1,
      "version": "7",
      "when": 1766236313648,
      "tag": "0001_wonderful_proteus",
      "breakpoints": true
    },
    {
      "idx": 2,
      "version": "7",
      "when": 1766816341635,
      "tag": "0002_public_mojo",
      "breakpoints": true
    },
    {
      "idx": 3,
      "version": "7",
      "when": 1767917000000,
      "tag": "0003_system_users",
      "breakpoints": true
    },
    {
      "idx": 4,
      "version": "7",
      "when": 1767524230156,
      "tag": "0004_tearful_quasimodo",
      "breakpoints": true
    }
  ]
}
